{
  "rows": 652500,
  "columns": [
    "Date",
    "Store",
    "Product",
    "Demand",
    "Price",
    "Promo"
  ],
  "date_range": [
    "2019-01-04 00:00:00",
    "2023-12-29 00:00:00"
  ],
  "stores": 50,
  "products": 50,
  "missing_values": 0,
  "demand_stats": {
    "mean": 204.4167754789272,
    "min": 20.0,
    "max": 653.0
  },
  "detected_columns": {
    "target": "Demand",
    "date": "Date",
    "has_store": true,
    "has_product": true,
    "has_holiday": false,
    "numeric_features": [
      "Price"
    ],
    "categorical_features": [
      "Promo"
    ]
  },
  "user_features": [
    "Price",
    "Promo"
  ]
}