{
  "confidence_intervals": {
    "coverage": 0.9988254777070064,
    "avg_width": 21.03318082138012
  },
  "timestamp": "2026-03-27T03:37:34.763631",
  "final_severity": "severe",
  "recommendation": "Severe drift detected: Fine-tuning applied",
  "months_monitored": 12,
  "severity_counts": {
    "severe": 12,
    "mild": 0,
    "none": 0
  },
  "healing_stats": {
    "total_actions": 12,
    "monitor_only": 0,
    "fine_tuned": 12,
    "rollbacks": 0
  },
  "avg_improvement": 0.4359,
  "train_metrics": {
    "RMSE": 1,
    "MAE": 1,
    "R2": 100,
    "MAPE": 1,
    "WMAPE": 1,
    "Accuracy": 99,
    "model": "XGB"
  },
  "feature_names": [
    "Price",
    "Promo",
    "Month",
    "Quarter",
    "Year",
    "DayOfYear",
    "WeekOfYear",
    "Is_Q1",
    "Is_Q2",
    "Is_Q3",
    "Is_Q4",
    "Month_Sin",
    "Month_Cos",
    "Quarter_Sin",
    "Quarter_Cos",
    "Week_Sin",
    "Week_Cos",
    "Near_Holiday",
    "Is_Summer",
    "Is_Winter",
    "Lag_1",
    "Lag_2",
    "Lag_3",
    "Lag_4",
    "Lag_6",
    "Lag_8",
    "Lag_12",
    "Rolling_Mean_3",
    "Rolling_Std_3",
    "Rolling_Max_3",
    "Rolling_Min_3",
    "Rolling_Mean_4",
    "Rolling_Std_4",
    "Rolling_Max_4",
    "Rolling_Min_4",
    "Rolling_Mean_6",
    "Rolling_Std_6",
    "Rolling_Max_6",
    "Rolling_Min_6",
    "Rolling_Mean_8",
    "Rolling_Std_8",
    "Rolling_Max_8",
    "Rolling_Min_8",
    "Rolling_Mean_12",
    "Rolling_Std_12",
    "Rolling_Max_12",
    "Rolling_Min_12",
    "Momentum_3",
    "Momentum_6",
    "Volatility_4",
    "Volatility_8",
    "Store_Mean",
    "Store_Std",
    "Demand_vs_Store_Mean",
    "Store_CV",
    "Product_Mean",
    "Product_Std",
    "Demand_vs_Product_Mean",
    "Product_CV",
    "Price_x_Promo",
    "Lag_1_x_Price",
    "Lag_1_x_Promo",
    "Lag_2_x_Price",
    "Lag_2_x_Promo",
    "Lag_3_x_Price",
    "Lag_3_x_Promo",
    "Rolling_Mean_3_x_Price",
    "Rolling_Mean_3_x_Promo",
    "Rolling_Mean_4_x_Price",
    "Rolling_Mean_4_x_Promo"
  ]
}